klrrrr/__init__.py
klrrrr/klrrrr.py
klrrrr-0.1.dist-info/METADATA
klrrrr-0.1.dist-info/WHEEL
klrrrr-0.1.dist-info/top_level.txt
klrrrr-0.1.dist-info/RECORD
